mitnewstools/__init__.py
mitnewstools/datemap.csv
mitnewstools/newsurlpatterns.csv
mit_news_tools-0.0.3.dist-info/LICENSE
mit_news_tools-0.0.3.dist-info/METADATA
mit_news_tools-0.0.3.dist-info/WHEEL
mit_news_tools-0.0.3.dist-info/top_level.txt
mit_news_tools-0.0.3.dist-info/RECORD
