Metadata-Version: 2.1
Name: mit-news-tools
Version: 0.0.3
Summary: tools to help people better understand the news
Home-page: https://github.mit.edu/Tegmark-Research-Group/mit-news-tools
Author: Emily Fan, Arun Wongprommoon, and Max Tegmark
Author-email: emilyfan@mit.edu
License: UNKNOWN
Platform: UNKNOWN
Classifier: Programming Language :: Python :: 3
Classifier: License :: OSI Approved :: GNU Affero General Public License v3
Classifier: Operating System :: OS Independent
Requires-Python: >=3.6
